odoo/addons/account_invoice_import/README.rst
odoo/addons/account_invoice_import/__init__.py
odoo/addons/account_invoice_import/__manifest__.py
odoo/addons/account_invoice_import/i18n/account_invoice_import.pot
odoo/addons/account_invoice_import/i18n/de.po
odoo/addons/account_invoice_import/i18n/es.po
odoo/addons/account_invoice_import/i18n/fr.po
odoo/addons/account_invoice_import/i18n/it.po
odoo/addons/account_invoice_import/i18n/nl.po
odoo/addons/account_invoice_import/i18n/sl.po
odoo/addons/account_invoice_import/images/sshot-wizard1.png
odoo/addons/account_invoice_import/migrations/16.0.2.0.0/post-migration.py
odoo/addons/account_invoice_import/migrations/16.0.2.0.0/pre-migration.py
odoo/addons/account_invoice_import/models/__init__.py
odoo/addons/account_invoice_import/models/account_journal.py
odoo/addons/account_invoice_import/models/account_move.py
odoo/addons/account_invoice_import/models/res_company.py
odoo/addons/account_invoice_import/models/res_partner.py
odoo/addons/account_invoice_import/readme/CONFIGURE.rst
odoo/addons/account_invoice_import/readme/CONTRIBUTORS.rst
odoo/addons/account_invoice_import/readme/DESCRIPTION.rst
odoo/addons/account_invoice_import/readme/ROADMAP.rst
odoo/addons/account_invoice_import/readme/USAGE.rst
odoo/addons/account_invoice_import/security/ir.model.access.csv
odoo/addons/account_invoice_import/static/description/icon.png
odoo/addons/account_invoice_import/static/description/index.html
odoo/addons/account_invoice_import/tests/__init__.py
odoo/addons/account_invoice_import/tests/test_invoice_import.py
odoo/addons/account_invoice_import/tests/pdf/unknown_invoice.pdf
odoo/addons/account_invoice_import/views/account_move.xml
odoo/addons/account_invoice_import/views/res_config_settings.xml
odoo/addons/account_invoice_import/views/res_partner.xml
odoo/addons/account_invoice_import/wizard/__init__.py
odoo/addons/account_invoice_import/wizard/account_invoice_import.py
odoo_addon_account_invoice_import-16.0.2.4.0.dist-info/METADATA
odoo_addon_account_invoice_import-16.0.2.4.0.dist-info/WHEEL
odoo_addon_account_invoice_import-16.0.2.4.0.dist-info/top_level.txt
odoo_addon_account_invoice_import-16.0.2.4.0.dist-info/RECORD
